
{
    "fileName": "LimelightHelpers-java.json",
    "name": "LimelightHelpers-java",
    "version": "v0.0.1",
    "uuid": "d7e0ab80-a8f6-11ed-9652-af5b67c789a5",
    "mavenUrls": ["https://raw.githubusercontent.com/snobotsim/maven_repo/limelight_Test/development"],
    "jsonUrl":    "https://raw.githubusercontent.com/snobotsim/maven_repo/limelight_Test/development/LimelightHelpers-java.json",
    "javaDependencies": [
      {
        "groupId": "io.limelightvision",
        "artifactId": "limelightlib-wpijava",
        "version": "v0.0.1"
      }
    ],
    "jniDependencies": [],
    "cppDependencies": []
  }
  
  